seckerwiki/__init__.py
seckerwiki/commands/__init__.py
seckerwiki/commands/git.py
seckerwiki/commands/journal.py
seckerwiki/commands/lecture.py
seckerwiki/commands/receipt.py
seckerwiki/commands/setup.py
seckerwiki/commands/stats.py
seckerwiki/commands/toc.py
seckerwiki/scripts/lecture_gen.py
seckerwiki/util.py
seckerwiki/wiki.py
seckerwiki-2.0.12.dist-info/entry_points.txt
seckerwiki-2.0.12.dist-info/LICENSE.txt
seckerwiki-2.0.12.dist-info/WHEEL
seckerwiki-2.0.12.dist-info/METADATA
seckerwiki-2.0.12.dist-info/RECORD
