Metadata-Version: 2.1
Name: seckerwiki
Version: 2.0.12
Summary: A collection of scripts used to manage my personal Foam workspace
Home-page: https://github.com/bsecker/wiki/
Author: Benjamin Secker
Author-email: benjamin.secker@gmail.com
Requires-Python: >=3.6,<4.0
Classifier: Programming Language :: Python :: 3
Classifier: Programming Language :: Python :: 3.10
Classifier: Programming Language :: Python :: 3.6
Classifier: Programming Language :: Python :: 3.7
Classifier: Programming Language :: Python :: 3.8
Classifier: Programming Language :: Python :: 3.9
Requires-Dist: PyInquirer (>=1.0.3,<2.0.0)
Requires-Dist: PyYAML (>=5.4.1,<6.0.0)
Requires-Dist: pdf2image (>=1.16.0,<2.0.0)
Requires-Dist: requests (>=2.26.0,<3.0.0)
Project-URL: Documentation, https://github.com/bsecker/wiki/blob/master/README.md
Project-URL: Repository, https://github.com/bsecker/wiki/
